README.md
setup.cfg
setup.py
geo_rendering/__init__.py
geo_rendering/contextual_text_class.py
geo_rendering/map_class.py
geo_rendering/point_class.py
geo_rendering/projection_class.py
geo_rendering/shape_class.py
geo_rendering/shapefile_class.py
geo_rendering/utility.py
geo_rendering.egg-info/PKG-INFO
geo_rendering.egg-info/SOURCES.txt
geo_rendering.egg-info/dependency_links.txt
geo_rendering.egg-info/not-zip-safe
geo_rendering.egg-info/requires.txt
geo_rendering.egg-info/top_level.txt
geo_rendering/tests/__init__.py
geo_rendering/tests/test.py