Metadata-Version: 2.1
Name: geo-rendering
Version: 1.0.0
Summary: Rendering of images from a shapefile using OpenCV
Home-page: https://github.com/acoullandreau/geo_rendering_package
Author: Alexina Coullandreau
License: MIT
Platform: UNKNOWN
Classifier: Development Status :: 4 - Beta
Classifier: License :: OSI Approved :: MIT License
Classifier: Programming Language :: Python :: 3
Classifier: Programming Language :: Python :: 3.7
Classifier: Intended Audience :: Developers
Classifier: Topic :: Multimedia :: Graphics
Classifier: Topic :: Multimedia :: Graphics :: Viewers
Classifier: Topic :: Scientific/Engineering :: Visualization
